{
  "id": "pressure_washing",
  "recipeId": "pressure_washing",
  "headline": "Let's bring the clean back to your property",
  "blurb": "Choose what you want washed.",
  "servicePrompt": "What would you like us to clean?",
  "trustLines": ["Satisfaction Guaranteed", "Flexible Scheduling", "Safe for Your Property"],
  "sidebarIncludes": ["Upfront pricing", "Instant quotes", "Licensed & insured", "100% satisfaction guarantee"],
  "helpBlurb": "Have questions? We're here to help!",
  "reviewTrust": "Powerful results. Property care you can see.",
  "cancelBlurb": "Reschedule up to 24 hours before we arrive.",
  "whereOptions": [
    {
      "id": "residential",
      "label": "Residential",
      "desc": "Homes & townhomes.",
      "image": "https://images.unsplash.com/photo-1600585154340-be6161a56a0c?auto=format&fit=crop&w=600&q=80"
    },
    {
      "id": "commercial",
      "label": "Commercial",
      "desc": "Offices, retail, lots.",
      "image": "https://images.unsplash.com/photo-1486406146926-c627a92ad1ab?auto=format&fit=crop&w=600&q=80"
    }
  ],
  "infoFields": [
    { "id": "sqft", "type": "text", "label": "Approx. sq ft (optional)", "optional": true },
    { "id": "surfaceNotes", "type": "textarea", "label": "Surface or access notes?", "optional": true },
    { "id": "referral", "type": "text", "label": "How did you hear about us?", "optional": true }
  ]
}
