{
  "milestone": "1.5",
  "epic": 5,
  "name": "Version & Rollback Engine",
  "title": "Version & Rollback Engine",
  "passed": true,
  "checkedAt": "2026-07-24T02:37:44.634Z",
  "proofs": {
    "versionEngineExists": true,
    "everyApprovedChangeCreatesVersion": true,
    "websiteVersions": true,
    "bookingVersions": true,
    "workspaceVersions": true,
    "automationVersions": true,
    "portfolioVersions": true,
    "versionComparison": true,
    "rollbackPlans": true,
    "partialRollback": true,
    "singleChangeRollback": true,
    "aiRestoreSuggestions": true,
    "businessTimeline": true,
    "missionControlVersionHistory": true,
    "noDirectRollbackExecution": true,
    "noApply": true,
    "demos": {
      "v1": {
        "id": "bver_mrybyexv_78i6yv",
        "label": "v1.1",
        "surfaces": [
          "website"
        ],
        "changes": [
          {
            "path": "website.premium_feel",
            "surface": "website",
            "before": false,
            "after": true,
            "builderOwner": "Website Builder",
            "summary": "Owner asked for a more premium website feel."
          },
          {
            "path": "website.hero.headline_tone",
            "surface": "website",
            "before": "clear",
            "after": "premium",
            "builderOwner": "Website Builder",
            "summary": "Premium feel usually starts with hero headline tone."
          }
        ]
      },
      "v2": {
        "id": "bver_mrybyexz_9805e6",
        "label": "v1.2",
        "surfaces": []
      },
      "diff": {
        "fromVersionId": "bver_mrybyexv_78i6yv",
        "toVersionId": "bver_mrybyexz_9805e6",
        "fromLabel": "v1.1",
        "toLabel": "v1.2",
        "surfaces": [
          {
            "surface": "website",
            "added": [],
            "removed": [
              {
                "path": "website.premium_feel",
                "surface": "website",
                "before": false,
                "after": true,
                "builderOwner": "Website Builder",
                "summary": "Owner asked for a more premium website feel."
              },
              {
                "path": "website.hero.headline_tone",
                "surface": "website",
                "before": "clear",
                "after": "premium",
                "builderOwner": "Website Builder",
                "summary": "Premium feel usually starts with hero headline tone."
              }
            ],
            "changed": []
          }
        ],
        "summary": "Compare v1.1 → v1.2: 2 diff(s)"
      },
      "fullRollback": {
        "id": "rb_mrybyey0_rl09hs",
        "scope": "full",
        "targetVersionId": "bver_mrybyexv_78i6yv",
        "targetLabel": "v1.1",
        "fromVersionId": "bver_mrybyexz_9805e6",
        "surfaces": [
          "website"
        ],
        "paths": [
          "website.premium_feel",
          "website.hero.headline_tone"
        ],
        "reason": "Go back to the first premium version.",
        "steps": [
          {
            "surface": "website",
            "path": "website.premium_feel",
            "restoreTo": true,
            "summary": "Restore website.premium_feel to v1.1"
          },
          {
            "surface": "website",
            "path": "website.hero.headline_tone",
            "restoreTo": "premium",
            "summary": "Restore website.hero.headline_tone to v1.1"
          }
        ],
        "requiresOwnerApproval": true,
        "executed": false,
        "applied": false,
        "status": "rollback_plan_ready",
        "waitingFor": "apply_engine",
        "createdAt": "2026-07-24T02:37:44.616Z"
      },
      "partialRollback": {
        "id": "rb_mrybyey0_icy4sr",
        "scope": "partial",
        "targetVersionId": "bver_mrybyexv_78i6yv",
        "targetLabel": "v1.1",
        "fromVersionId": "bver_mrybyexz_9805e6",
        "surfaces": [
          "booking"
        ],
        "paths": [],
        "reason": "Restore only the booking changes.",
        "steps": [],
        "requiresOwnerApproval": true,
        "executed": false,
        "applied": false,
        "status": "rollback_plan_ready",
        "waitingFor": "apply_engine",
        "createdAt": "2026-07-24T02:37:44.616Z"
      },
      "singleRollback": {
        "id": "rb_mrybyey0_khhwl7",
        "scope": "single",
        "targetVersionId": "bver_mrybyexv_78i6yv",
        "targetLabel": "v1.1",
        "fromVersionId": "bver_mrybyexz_9805e6",
        "surfaces": [
          "website"
        ],
        "paths": [
          "website.premium_feel"
        ],
        "reason": "Undo only one change.",
        "steps": [
          {
            "surface": "website",
            "path": "website.premium_feel",
            "restoreTo": true,
            "summary": "Single-change rollback: website.premium_feel"
          }
        ],
        "requiresOwnerApproval": true,
        "executed": false,
        "applied": false,
        "status": "rollback_plan_ready",
        "waitingFor": "apply_engine",
        "createdAt": "2026-07-24T02:37:44.616Z"
      },
      "restoreSuggestions": [
        {
          "id": "restore_mrybyey0_mfj7wk",
          "suggestedVersionId": "bver_mrybyexv_78i6yv",
          "suggestedLabel": "v1.1",
          "currentVersionId": "bver_mrybyexz_9805e6",
          "reason": "I think v1.1 may have performed better for trust signals.",
          "signal": "Conversions / trust may have softened after the latest homepage change.",
          "confidence": 90,
          "requiresOwnerApproval": true,
          "autoApplied": false
        }
      ],
      "timeline": {
        "businessId": "biz_epic5_founder",
        "title": "Business Timeline",
        "events": [
          {
            "id": "tl_mrybyexv_k52uhi",
            "at": "2026-07-12T02:37:44.611Z",
            "kind": "milestone",
            "emoji": "🎉",
            "title": "Website launched",
            "detail": "First public Hubly site went live.",
            "versionId": null,
            "versionLabel": null
          },
          {
            "id": "tl_mrybyexv_c1xhto",
            "at": "2026-07-13T02:37:44.611Z",
            "kind": "integration",
            "emoji": "💳",
            "title": "Stripe connected",
            "detail": "Card pay on booking enabled.",
            "versionId": null,
            "versionLabel": null
          },
          {
            "id": "tl_mrybyexv_yuufh7",
            "at": "2026-07-14T02:37:44.611Z",
            "kind": "builder_change",
            "emoji": "📅",
            "title": "Arrival windows enabled",
            "detail": "Booking rules updated for clearer ETAs.",
            "versionId": null,
            "versionLabel": null
          },
          {
            "id": "tl_mrybyexv_ne17fe",
            "at": "2026-07-16T02:37:44.611Z",
            "kind": "achievement",
            "emoji": "⭐",
            "title": "First 5-star review",
            "detail": "Proof that trust is compounding.",
            "versionId": null,
            "versionLabel": null
          },
          {
            "id": "tl_mrybyexv_eoso02",
            "at": "2026-07-22T02:37:44.611Z",
            "kind": "growth",
            "emoji": "🏆",
            "title": "100th booking",
            "detail": "A growth moment worth celebrating.",
            "versionId": null,
            "versionLabel": null
          },
          {
            "id": "tl_mrybyexv_qpqzwo",
            "at": "2026-07-24T02:37:44.611Z",
            "kind": "ai_recommendation",
            "emoji": "🧠",
            "title": "Hubly recommends launching memberships",
            "detail": "Next chapter for biz_epic5_founder — owner decides.",
            "versionId": null,
            "versionLabel": null
          },
          {
            "id": "tl_mrybyexv_xn0x9l",
            "at": "2026-07-24T02:37:44.611Z",
            "kind": "builder_change",
            "emoji": "📈",
            "title": "v1.1 — Website Improvement",
            "detail": "Owner asked for a more premium website feel.; Premium feel usually starts with hero headline tone.",
            "versionId": "bver_mrybyexv_78i6yv",
            "versionLabel": "v1.1"
          },
          {
            "id": "tl_mrybyexz_6xubi8",
            "at": "2026-07-24T02:37:44.615Z",
            "kind": "builder_change",
            "emoji": "📈",
            "title": "v1.2 — Business Change",
            "detail": "",
            "versionId": "bver_mrybyexz_9805e6",
            "versionLabel": "v1.2"
          }
        ],
        "storyNote": "Not just what changed — how the business evolved. Builder changes, milestones, achievements, and Hubly recommendations."
      },
      "surfaces": [
        {
          "id": "booking",
          "request": "Add arrival windows.",
          "version": {
            "id": "bver_mrybyey8_9i5su3",
            "label": "v1.1",
            "surfaces": [
              "booking"
            ],
            "changes": [
              {
                "path": "booking.arrival_window",
                "surface": "booking",
                "before": {
                  "enabled": false,
                  "before_minutes": 0,
                  "after_minutes": 0
                },
                "after": {
                  "enabled": true,
                  "before_minutes": 60,
                  "after_minutes": 60
                },
                "builderOwner": "Booking Builder",
                "summary": "Owner wants appointment arrival windows."
              }
            ],
            "reason": "Approved direction: Booking Rule",
            "builders": [
              "Booking Builder"
            ],
            "applied": false
          },
          "passed": true
        },
        {
          "id": "workspace",
          "request": "Move Jobs above Customers.",
          "version": {
            "id": "bver_mrybyeya_ttw0ji",
            "label": "v1.1",
            "surfaces": [
              "workspace"
            ],
            "changes": [
              {
                "path": "workspace.sidebar_order",
                "surface": "workspace",
                "before": [
                  "Customers",
                  "Jobs",
                  "Calendar"
                ],
                "after": [
                  "Jobs",
                  "Customers"
                ],
                "builderOwner": "Workspace Builder",
                "summary": "Owner wants Jobs above Customers in navigation."
              }
            ],
            "reason": "Approved direction: Workspace Layout",
            "builders": [
              "Workspace Builder"
            ],
            "applied": false
          },
          "passed": true
        },
        {
          "id": "portfolio",
          "request": "Organize my portfolio.",
          "version": {
            "id": "bver_mrybyeyc_zcjpj8",
            "label": "v1.1",
            "surfaces": [
              "portfolio"
            ],
            "changes": [
              {
                "path": "portfolio.gallery.organize",
                "surface": "portfolio",
                "before": false,
                "after": true,
                "builderOwner": "Portfolio Builder",
                "summary": "Owner wants portfolio photos organized in the gallery."
              }
            ],
            "reason": "Approved direction: Portfolio Update",
            "builders": [
              "Portfolio Builder"
            ],
            "applied": false
          },
          "passed": true
        },
        {
          "id": "automation",
          "request": "Send prep instructions after ceramic coating bookings.",
          "version": {
            "id": "bver_mrybyeye_jvyjjy",
            "label": "v1.1",
            "surfaces": [
              "automations"
            ],
            "changes": [
              {
                "path": "automations.workflows",
                "surface": "automations",
                "before": [],
                "after": [
                  {
                    "id": "prep_after_ceramic",
                    "trigger": "booking.completed.service:ceramic_coating",
                    "steps": [
                      {
                        "type": "createWorkflow",
                        "config": {
                          "name": "Ceramic coating prep"
                        }
                      },
                      {
                        "type": "sendEmail",
                        "config": {
                          "template": "prep_instructions"
                        }
                      },
                      {
                        "type": "wait",
                        "config": {
                          "hours": 0
                        }
                      },
                      {
                        "type": "sendReminder",
                        "config": {
                          "channel": "email"
                        }
                      }
                    ]
                  }
                ],
                "builderOwner": "Automation Builder",
                "summary": "Send prep instructions after ceramic coating bookings."
              }
            ],
            "reason": "Approved direction: Automation Setup",
            "builders": [
              "Automation Builder"
            ],
            "applied": false
          },
          "passed": true
        }
      ]
    }
  },
  "failures": null
}
